README.md
requirements.txt
setup.py
cvmodelz/__init__.py
cvmodelz/_version.py
cvmodelz/model_info.py
cvmodelz.egg-info/PKG-INFO
cvmodelz.egg-info/SOURCES.txt
cvmodelz.egg-info/dependency_links.txt
cvmodelz.egg-info/not-zip-safe
cvmodelz.egg-info/requires.txt
cvmodelz.egg-info/top_level.txt
cvmodelz/classifiers/__init__.py
cvmodelz/classifiers/base.py
cvmodelz/classifiers/separate_model_classifier.py
cvmodelz/models/__init__.py
cvmodelz/models/base.py
cvmodelz/models/factory.py
cvmodelz/models/meta_info.py
cvmodelz/models/prepare_type.py
cvmodelz/models/wrapper.py
cvmodelz/models/prepare/__init__.py
cvmodelz/models/prepare/functions.py
cvmodelz/models/prepare/types.py
cvmodelz/models/pretrained/__init__.py
cvmodelz/models/pretrained/base.py
cvmodelz/models/pretrained/resnet.py
cvmodelz/models/pretrained/vgg.py
cvmodelz/models/pretrained/inception/__init__.py
cvmodelz/models/pretrained/inception/blocks.py
cvmodelz/models/pretrained/inception/inception_v3.py
cvmodelz/models/pretrained/inception/inception_v3_hd.py
cvmodelz/models/pretrained/inception/link_mappings.py
cvmodelz/utils/__init__.py
cvmodelz/utils/functions/__init__.py
cvmodelz/utils/functions/alpha_product.py
cvmodelz/utils/functions/signed_square_root.py
cvmodelz/utils/functions/tf_average.py
cvmodelz/utils/links/__init__.py
cvmodelz/utils/links/pooling/__init__.py
cvmodelz/utils/links/pooling/alpha_pooling.py
cvmodelz/utils/links/pooling/compact_bilinear.py
cvmodelz/utils/links/pooling/global_average.py
tests/test_utils.py