Metadata-Version: 2.1
Name: cvmodelz
Version: 0.4.0
Summary: Wrapper for various computer vision models (mostly provided by chainer, chainercv, and chainercv2)
Author: Dimitri Korsch
Author-email: korschdima@gmail.com
License: MIT License
Requires-Python: >3.7
